decypher/__init__.py
decypher/__main__.py
decypher/cli.py
decypher/home.py
decypher-1.0.0.dist-info/entry_points.txt
decypher-1.0.0.dist-info/METADATA
decypher-1.0.0.dist-info/WHEEL
decypher-1.0.0.dist-info/RECORD
