Metadata-Version: 2.1
Name: decypher
Version: 1.0.0
Summary: 
Author: R Aswin
Author-email: aswinr242004@gmail.com
Requires-Python: >=3.12,<4.0
Classifier: Programming Language :: Python :: 3
Classifier: Programming Language :: Python :: 3.12
Requires-Dist: typer[all] (>=0.9.0,<0.10.0)
